AirCommand/__init__.py
AirCommand/main.py
aircommand-0.1.0.dist-info/METADATA
aircommand-0.1.0.dist-info/WHEEL
aircommand-0.1.0.dist-info/top_level.txt
aircommand-0.1.0.dist-info/RECORD
