Metadata-Version: 2.4
Name: AirCommand
Version: 0.1.0
Summary: Control media players like Youtube, VLC, and Spotify using hand gestures.
Home-page: https://github.com/akshit0942b/AirCommand
Author: Akshit
Author-email: akshitprajapati24@gmail.com
Classifier: Programming Language :: Python :: 3
Classifier: License :: OSI Approved :: MIT License
Classifier: Operating System :: MacOS
Classifier: Operating System :: MacOS :: MacOS X
Requires-Python: >=3.7
Requires-Dist: opencv-python
Requires-Dist: mediapipe
Requires-Dist: pyautogui
Dynamic: author
Dynamic: author-email
Dynamic: classifier
Dynamic: description-content-type
Dynamic: home-page
Dynamic: requires-dist
Dynamic: requires-python
Dynamic: summary
